add_simple_package/__init__.py
add_simple_package/addition_arrays.py
add_simple_package/addition_scalars.py
add_simple_package/use.py
add_simple_package-0.2.6.dist-info/METADATA
add_simple_package-0.2.6.dist-info/WHEEL
add_simple_package-0.2.6.dist-info/top_level.txt
add_simple_package-0.2.6.dist-info/RECORD
